LICENSE.md
MANIFEST.in
README.md
requirements.txt
setup.py
mastotron/__init__.py
mastotron/cli.py
mastotron/db.py
mastotron/graphdb.py
mastotron/htmlfmt.py
mastotron/imports.py
mastotron/mastotron.py
mastotron/post.py
mastotron/poster.py
mastotron/postlist.py
mastotron/postnet.py
mastotron/utils.py
mastotron.egg-info/PKG-INFO
mastotron.egg-info/SOURCES.txt
mastotron.egg-info/dependency_links.txt
mastotron.egg-info/entry_points.txt
mastotron.egg-info/requires.txt
mastotron.egg-info/top_level.txt
mastotron/gui/__init__.py
mastotron/gui/app.py
mastotron/gui/static/dalle2b-small.png
mastotron/gui/static/dalle3-small.png
mastotron/gui/static/dalle3-transp-small.ico
mastotron/gui/static/dalle3-transp-small.png
mastotron/gui/static/dark-mode-6682-inv.png
mastotron/gui/static/dark-mode-6682.png
mastotron/gui/static/drawnet0.js
mastotron/gui/static/jquery-latest.min.js
mastotron/gui/static/jquery-ui.css
mastotron/gui/static/jquery-ui.js
mastotron/gui/static/jquery.flash.css
mastotron/gui/static/jquery.flash.js
mastotron/gui/static/knobs.js
mastotron/gui/static/login.js
mastotron/gui/static/nightmode.jpg
mastotron/gui/static/postnet.css
mastotron/gui/static/postnet.js
mastotron/gui/static/prompt-boxes.min.css
mastotron/gui/static/prompt-boxes.min.css.map
mastotron/gui/static/prompt-boxes.min.js
mastotron/gui/static/prompt-boxes.min.js.map
mastotron/gui/static/socket.io.js
mastotron/gui/static/socket.io.js.map
mastotron/gui/static/spinners.mjs
mastotron/gui/static/utils.js
mastotron/gui/static/vis-network.min.js
mastotron/gui/static/vis-network.min.js.map
mastotron/gui/templates/code.html
mastotron/gui/templates/layout.html
mastotron/gui/templates/login.html
mastotron/gui/templates/postnet-all.html
mastotron/gui/templates/postnet.html