Metadata-Version: 2.1
Name: mastotron
Version: 0.4.6
Summary: Algorithmifying mastodon
Home-page: https://github.com/quadrismegistus/mastotron
Author: Ryan Heuser
Author-email: ryan.heuser@princeton.edu
License: MIT
Platform: UNKNOWN
Classifier: Development Status :: 2 - Pre-Alpha
Classifier: License :: OSI Approved :: MIT License
Classifier: Programming Language :: Python
Classifier: Programming Language :: Python :: 2
Classifier: Programming Language :: Python :: 2.7
Classifier: Programming Language :: Python :: 3
Classifier: Programming Language :: Python :: 3.4
Classifier: Programming Language :: Python :: 3.5
Classifier: Programming Language :: Python :: 3.6
Classifier: Programming Language :: Python :: 3.7
